.dockerignore
.gitignore
CMakeLists.txt
Dockerfile
LICENSE.LGPL
MANIFEST.in
README.md
setup.py
.github/workflows/ci.yaml
.github/workflows/release.yaml
apps/CMakeLists.txt
apps/main.c
apps/main.py
cmake/FindFFTW.cmake
cmake/FindPulseAudio.cmake
dev/audiosync_sketch.py
dev/benchmark.py
dev/getaudio.sh
dev/pulseaudio_setup_sketch.bash
dev/run-tests-docker.sh
images/144000.png
images/144000_original.png
images/288000.png
images/288000_original.png
images/480000.png
images/480000_original.png
images/cross_correlation.png
images/demo.gif
images/demo.mp4
include/audiosync/audiosync.h
include/audiosync/cross_correlation.h
include/audiosync/ffmpeg_pipe.h
include/audiosync/capture/linux_capture.h
include/audiosync/download/linux_download.h
src/CMakeLists.txt
src/audiosync.c
src/bind.c
src/cross_correlation.c
src/ffmpeg_pipe.c
src/capture/linux_capture.c
src/download/linux_download.c
tests/CMakeLists.txt
tests/test_bindings.py
tests/test_cross_correlation.c
tests/test_pearson_coefficient.c
tests/test_pulseaudio_setup.c
tests/test_pulseaudio_setup_wrapper.sh
vidify_audiosync.egg-info/PKG-INFO
vidify_audiosync.egg-info/SOURCES.txt
vidify_audiosync.egg-info/dependency_links.txt
vidify_audiosync.egg-info/top_level.txt