Metadata-Version: 2.1
Name: vidify-audiosync
Version: 0.3.0
Summary: Vidify extension to synchronize a YouTube video with the audio playing on your device.
Home-page: https://github.com/marioortizmanero/vidify-audiosync
Author: Mario O.M.
Author-email: marioortizmanero@gmail.com
Maintainer: Mario O.M.
Maintainer-email: marioortizmanero@gmail.com
License: LGPL
Keywords: audio synchronization cross-correlation pearson coefficient fft signal-processing ffmpeg youtube-dl fftw
Platform: UNKNOWN
Classifier: Development Status :: 3 - Alpha
Classifier: Intended Audience :: End Users/Desktop
Classifier: Topic :: Multimedia :: Sound/Audio :: Analysis
Classifier: License :: OSI Approved :: GNU Lesser General Public License v3 (LGPLv3)
Classifier: Programming Language :: C
Requires-Python: >=3.5
